README.md
setup.py
cfn_inspect/__init__.py
cfn_inspect/__main__.py
cfn_inspect/__version__.py
cfn_inspect/cli.py
cfn_inspect.egg-info/PKG-INFO
cfn_inspect.egg-info/SOURCES.txt
cfn_inspect.egg-info/dependency_links.txt
cfn_inspect.egg-info/entry_points.txt
cfn_inspect.egg-info/requires.txt
cfn_inspect.egg-info/top_level.txt