Metadata-Version: 1.1
Name: cfn-inspect
Version: 0.2.6
Summary: CloudFormation printer and inspector
Home-page: https://github.com/tdi/cfn-inspect
Author: Dariusz Dwornikowski
Author-email: dariusz.dwornikowski@nordcloud.com
License: MIT
Platform: UNKNOWN
Classifier: License :: OSI Approved :: MIT License
Classifier: Programming Language :: Python
Classifier: Programming Language :: Python :: 2.7
Classifier: Programming Language :: Python :: 3
Classifier: Programming Language :: Python :: 3.3
Classifier: Programming Language :: Python :: 3.4
Classifier: Programming Language :: Python :: 3.5
Classifier: Programming Language :: Python :: 3.6
Classifier: Programming Language :: Python :: Implementation :: CPython
Classifier: Programming Language :: Python :: Implementation :: PyPy
